data/README.md
data/__init__.py
data/idl_3.csv
data/look_and_say.dat
data/sunback_server.log
devtools/README.md
devtools/__init__.py
devtools/conda-envs/pick_env.py
devtools/conda-envs/start_coverage.py
devtools/conda-envs/stop_coverage.py
devtools/conda-envs/test_env.yaml
devtools/conda-envs/test_env_mac.yaml
devtools/scripts/__init__.py
devtools/scripts/buildDistribution.bat
devtools/scripts/create_conda_env.py
devtools/scripts/fullUpload.bat
devtools/scripts/git-filter-repo.py
devtools/scripts/testUpload.bat
devtools/travis-ci/before_install.sh
docs/Makefile
docs/README.md
docs/__init__.py
docs/all-about-me.rst
docs/api.rst
docs/conf.py
docs/errlog.txt
docs/getting_started.rst
docs/index.rst
docs/make.bat
docs/requirements.txt
docs/_templates/README.md
docs/_templates/__init__.py
docs/_templates/layout.html
docs/autosummary/__init__.py
docs/autosummary/sunback.Parameters.rst
docs/autosummary/sunback.Sunback.rst
resources/__init__.py
resources/soundscapeLoutrakiSunset.mid
resources/panHelio/__init__.py
resources/panHelio/aia_netCDF_gen.py
resources/panHelio/download_RT_aia.py
resources/panHelio/utils.py
sunback/__init__.py
sunback/_version.py
sunback/log.txt
sunback/openh264-1.8.0-win64.dll
sunback/setup.cfg
sunback/time.txt
sunback/versioneer.py
sunback/__tests__/__init__.py
sunback/__tests__/errlog.txt
sunback/__tests__/test registry.py
sunback/__tests__/test_171.jpg
sunback/__tests__/test_parameters.py
sunback/__tests__/test_sunback.py
sunback/fetcher/ADAPTClient.py
sunback/fetcher/AIASynopticClient.py
sunback/fetcher/AIASynopticClient_Bkk.py
sunback/fetcher/AIASynopticClient_broken.py
sunback/fetcher/AIASynopticClient_working.py
sunback/fetcher/AwsImgFetcher.py
sunback/fetcher/AwsImgFetcher.pybkk
sunback/fetcher/Fetcher Scratch
sunback/fetcher/Fetcher.py
sunback/fetcher/FidoFetcher.py
sunback/fetcher/FidoSynopticFetcher.py
sunback/fetcher/FidoSynopticFetcher_Bkk.py
sunback/fetcher/FidoSynopticFetcher_working.py
sunback/fetcher/FidoTimeIntProcessor.py
sunback-0.6.17.dist-info/LICENSE
sunback-0.6.17.dist-info/METADATA
sunback-0.6.17.dist-info/WHEEL
sunback-0.6.17.dist-info/entry_points.txt
sunback-0.6.17.dist-info/top_level.txt
sunback-0.6.17.dist-info/RECORD
