Metadata-Version: 2.2
Name: sunback
Version: 0.6.17
Summary: Sets your desktop background to the most recent images of the Sun.
Home-page: https://github.com/GillySpace27/sunback
Author: C. R. Gilly
Author-email: "C. R. Gilly" <chris.gilly@colorado.edu>
License: BSD-3-Clause
Project-URL: Homepage, https://github.com/GillySpace27/sunback
Classifier: Development Status :: 4 - Beta
Classifier: Intended Audience :: End Users/Desktop
Classifier: Intended Audience :: Science/Research
Classifier: Topic :: Desktop Environment
Classifier: Topic :: Desktop Environment :: Screen Savers
Classifier: Topic :: Multimedia :: Graphics :: Viewers
Classifier: License :: OSI Approved :: BSD License
Classifier: Programming Language :: Python :: 3 :: Only
Classifier: Operating System :: Microsoft :: Windows
Classifier: Operating System :: POSIX
Classifier: Operating System :: MacOS
Requires-Python: >=3.0
License-File: LICENSE
Requires-Dist: boto3
Requires-Dist: matplotlib
Requires-Dist: sunpy
Requires-Dist: astropy
Requires-Dist: scipy
Requires-Dist: opencv-python
Requires-Dist: xarray
Requires-Dist: requests
Provides-Extra: test
Requires-Dist: pytest; extra == "test"
Requires-Dist: pytest-runner; extra == "test"
Provides-Extra: server
Requires-Dist: twine; extra == "server"
Requires-Dist: pillow; extra == "server"
Requires-Dist: appscript; platform_system == "Darwin" and extra == "server"
Requires-Dist: moviepy; extra == "server"
Requires-Dist: parfive; extra == "server"
Requires-Dist: beautifulsoup4; extra == "server"
Requires-Dist: html5lib; extra == "server"
Requires-Dist: numpy; extra == "server"
Requires-Dist: sunkit-image; extra == "server"
Requires-Dist: aiapy; extra == "server"
Dynamic: author
Dynamic: home-page
Dynamic: requires-python
